longPolling/__init__.py
longPolling/client.py
longPolling/server.py
longPolling-0.0.4.dist-info/METADATA
longPolling-0.0.4.dist-info/WHEEL
longPolling-0.0.4.dist-info/top_level.txt
longPolling-0.0.4.dist-info/RECORD
