Metadata-Version: 2.1
Name: longPolling
Version: 0.0.4
Summary: Simple long polling implementation
Home-page: https://kuankuan2007.gitee.io/docs/long-polling/
Author: kuankuan
Author-email: 2163826131@qq.com
License: Mulan PSL v2
Keywords: long polling,flask,http,thread
Platform: windows
Platform: linux
Platform: macos
Classifier: Development Status :: 3 - Alpha
Classifier: Intended Audience :: Developers
Classifier: Programming Language :: Python :: 3
Classifier: Operating System :: MacOS
Classifier: Operating System :: POSIX :: Linux
Classifier: Operating System :: Microsoft :: Windows
Classifier: License :: OSI Approved :: Mulan Permissive Software License v2 (MulanPSL-2.0)
Requires-Dist: requests
Requires-Dist: flask
Requires-Dist: rsa
